{
  "project_info": {
    "project_number": "305255592089",
    "project_id": "mydigitalproject-80b5b",
    "storage_bucket": "mydigitalproject-80b5b.appspot.com"
  },
  "client": [
    {
      "client_info": {
        "mobilesdk_app_id": "1:305255592089:android:3b610bf7b4fe87d0e7c808",
        "android_client_info": {
          "package_name": "com.example.mds_project"
        }
      },
      "oauth_client": [
        {
          "client_id": "305255592089-t8qhtu9u97skifv20jsh9agklm2nm9q1.apps.googleusercontent.com",
          "client_type": 3
        }
      ],
      "api_key": [
        {
          "current_key": "AIzaSyDJ-Mtb561Cf9H9VCsL3QSoRn5EZ3vO7ds"
        }
      ],
      "services": {
        "appinvite_service": {
          "other_platform_oauth_client": [
            {
              "client_id": "305255592089-t8qhtu9u97skifv20jsh9agklm2nm9q1.apps.googleusercontent.com",
              "client_type": 3
            }
          ]
        }
      }
    }
  ],
  "configuration_version": "1"
}